[
  {
    "id": 1,
    "name": "游戏",
    "items": [
      {
        "id": 2101,
        "name": "公路",
        "url": [
          "res/drawable/b_101.png"
        ]
      },
      {
        "id": 2102,
        "name": "土地",
        "url": [
          "res/drawable/b_102.png"
        ]
      },
      {
        "id": 2103,
        "name": "天空",
        "url": [
          "res/drawable/b_103.png"
        ]
      },
      {
        "id": 2104,
        "name": "太空",
        "url": [
          "res/drawable/b_104.jpg"
        ]
      },
      {
        "id": 2105,
        "name": "宇宙",
        "url": [
          "res/drawable/b_105.png"
        ]
      },
      {
        "id": 2106,
        "name": "平原赛道",
        "url": [
          "res/drawable/b_106.jpg"
        ]
      },
      {
        "id": 2107,
        "name": "循环草地",
        "url": [
          "res/drawable/b_107.jpg"
        ]
      },
      {
        "id": 2108,
        "name": "抽奖背景",
        "url": [
          "res/drawable/b_108.jpg"
        ]
      },
      {
        "id": 2109,
        "name": "摇一摇",
        "url": [
          "res/drawable/b_109.png"
        ]
      },
      {
        "id": 2110,
        "name": "擂台",
        "url": [
          "res/drawable/b_110.png"
        ]
      },
      {
        "id": 2111,
        "name": "桥",
        "url": [
          "res/drawable/b_111.png"
        ]
      },
      {
        "id": 2112,
        "name": "源码画板",
        "url": [
          "res/drawable/b_112.png"
        ]
      },
      {
        "id": 2113,
        "name": "猫爪印",
        "url": [
          "res/drawable/b_113.png"
        ]
      },
      {
        "id": 2114,
        "name": "白天背景",
        "url": [
          "res/drawable/b_114.png"
        ]
      },
      {
        "id": 2115,
        "name": "科学空间",
        "url": [
          "res/drawable/b_115.jpg"
        ]
      },
      {
        "id": 2116,
        "name": "篮框背景",
        "url": [
          "res/drawable/b_116.png"
        ]
      },
      {
        "id": 2117,
        "name": "编程猫背景",
        "url": [
          "res/drawable/b_117.png"
        ]
      },
      {
        "id": 2118,
        "name": "蔬菜地",
        "url": [
          "res/drawable/b_118.png"
        ]
      },
      {
        "id": 2119,
        "name": "踏青河流",
        "url": [
          "res/drawable/b_119.png"
        ]
      },
      {
        "id": 2120,
        "name": "雪天道路",
        "url": [
          "res/drawable/b_120.png"
        ]
      },
      {
        "id": 2121,
        "name": "抽奖机",
        "url": [
          "res/drawable/b_121.jpg"
        ]
      },
      {
        "id": 2122,
        "name": "木板背景",
        "url": [
          "res/drawable/b_122.jpg"
        ]
      },
      {
        "id": 2123,
        "name": "足球场",
        "url": [
          "res/drawable/b_123.jpg"
        ]
      },
      {
        "id": 2124,
        "name": "跑道",
        "url": [
          "res/drawable/b_124.jpg"
        ]
      },
      {
        "id": 2125,
        "name": "色彩冷",
        "url": [
          "res/drawable/b_125.png"
        ]
      },
      {
        "id": 2126,
        "name": "色彩暖",
        "url": [
          "res/drawable/b_126.png"
        ]
      },
      {
        "id": 2127,
        "name": "纯色",
        "url": [
          "res/drawable/b_127.png"
        ]
      },
      {
        "id": 2128,
        "name": "黑白配",
        "url": [
          "res/drawable/b_128.png"
        ]
      },
      {
        "id": 2129,
        "name": "蓝色格子",
        "url": [
          "res/drawable/b_129.png"
        ]
      },
      {
        "id": 2130,
        "name": "量角器",
        "url": [
          "res/drawable/b_130.png"
        ]
      },
      {
        "id": 2131,
        "name": "器械水印",
        "url": [
          "res/drawable/b_131.png"
        ]
      },
      {
        "id": 2132,
        "name": "数字水印",
        "url": [
          "res/drawable/b_132.png"
        ]
      },
      {
        "id": 2133,
        "name": "生日快乐",
        "url": [
          "res/drawable/b_133.png"
        ]
      },
      {
        "id": 2134,
        "name": "翠橙宇宙",
        "url": [
          "res/drawable/b_134.jpg"
        ]
      },
      {
        "id": 2135,
        "name": "湛蓝宇宙",
        "url": [
          "res/drawable/b_135.jpg"
        ]
      },
      {
        "id": 2136,
        "name": "幻紫宇宙",
        "url": [
          "res/drawable/b_136.jpg"
        ]
      },
      {
        "id": 2137,
        "name": "数码-青山",
        "url": [
          "res/drawable/b_137.jpg"
        ]
      },
      {
        "id": 2138,
        "name": "数码-秋天",
        "url": [
          "res/drawable/b_138.jpg"
        ]
      },
      {
        "id": 2139,
        "name": "数码-沙滩",
        "url": [
          "res/drawable/b_139.jpg"
        ]
      },
      {
        "id": 2140,
        "name": "数码-天空",
        "url": [
          "res/drawable/b_140.jpg"
        ]
      },
      {
        "id": 2141,
        "name": "数码-晚霞",
        "url": [
          "res/drawable/b_141.jpg"
        ]
      },
      {
        "id": 2142,
        "name": "数码-星空",
        "url": [
          "res/drawable/b_142.jpg"
        ]
      },
      {
        "id": 2143,
        "name": "紫色圆点",
        "url": [
          "res/drawable/b_143.jpg"
        ]
      },
      {
        "id": 2144,
        "name": "蓝色天空",
        "url": [
          "res/drawable/b_144.png"
        ]
      },
      {
        "id": 2145,
        "name": "林间小路",
        "url": [
          "res/drawable/b_145.png"
        ]
      }
    ]
  }
]